docs/conf.py
tlverifier/__init__.py
tlverifier/requirements.txt
tlverifier/merkle_functions/__init__.py
tlverifier/merkle_functions/data_access.py
tlverifier/merkle_functions/testers.py
tlverifier/merkle_functions/tl_functions.py
tlverifier/merkle_functions/tree_mocker.py
tlverifier/mock/mock_dev/v3/all_consistency_proof_global.json
tlverifier/mock/mock_dev/v3/all_consistency_proof_tree1.json
tlverifier/mock/mock_dev/v3/all_leaf_global_tree.json
tlverifier/mock/mock_dev/v3/partial_global_roots.json
tlverifier/mock/mock_dev/v3/t1_proof_leaf11.json
tlverifier/mock/mock_dev/v3/t1_root.json
tlverifier/mock/mock_dev/v3/tg_proof_root1.json
tlverifier/mock/mock_dev/v3/tg_root.json
tlverifier-0.0.28.dist-info/LICENSE
tlverifier-0.0.28.dist-info/METADATA
tlverifier-0.0.28.dist-info/WHEEL
tlverifier-0.0.28.dist-info/top_level.txt
tlverifier-0.0.28.dist-info/RECORD
