Metadata-Version: 2.1
Name: tlverifier
Version: 0.0.28
Summary: Tool for transparent logs
Author-email: "K. A. Khalil" <kha.devel@gmail.com>
Project-URL: Homepage, https://github.com/larc-logs-transparentes/tlverifier.git
Classifier: Programming Language :: Python :: 3
Classifier: License :: OSI Approved :: MIT License
Classifier: Operating System :: OS Independent
Requires-Python: >=3.7
License-File: LICENSE
Requires-Dist: pymerkle-logsTransparentes ~=0.0.3
